typedthon/__init__.py
typedthon-0.0.1.dist-info/LICENSE
typedthon-0.0.1.dist-info/METADATA
typedthon-0.0.1.dist-info/WHEEL
typedthon-0.0.1.dist-info/top_level.txt
typedthon-0.0.1.dist-info/RECORD
