Metadata-Version: 2.1
Name: typedthon
Version: 0.0.1
Summary: Something to do with python and types
Author-email: Alok Singh <alokbeniwal@gmail.com>
Classifier: Programming Language :: Python :: 3
Classifier: License :: OSI Approved :: MIT License
Classifier: Operating System :: OS Independent
Requires-Python: >=3.11
License-File: LICENSE
